e32/__init__.py
e32/cli.py
e32/assets/example.txt
e32-1.0.0.dist-info/LICENSE
e32-1.0.0.dist-info/METADATA
e32-1.0.0.dist-info/WHEEL
e32-1.0.0.dist-info/entry_points.txt
e32-1.0.0.dist-info/top_level.txt
e32-1.0.0.dist-info/RECORD
